ffmpeg_bitrate_stats/__init__.py
ffmpeg_bitrate_stats/__main__.py
ffmpeg_bitrate_stats/bitrate_stats.py
ffmpeg_bitrate_stats/log.py
ffmpeg_bitrate_stats/py.typed
ffmpeg_bitrate_stats-1.3.1.dist-info/licenses/LICENSE.md
ffmpeg_bitrate_stats-1.3.1.dist-info/WHEEL
ffmpeg_bitrate_stats-1.3.1.dist-info/entry_points.txt
ffmpeg_bitrate_stats-1.3.1.dist-info/METADATA
ffmpeg_bitrate_stats-1.3.1.dist-info/RECORD
