Metadata-Version: 2.4
Name: ffmpeg-bitrate-stats
Version: 1.3.1
Summary: Calculate bitrate statistics using FFmpeg
Author: Werner Robitza
Author-email: Werner Robitza <werner.robitza@gmail.com>
License-Expression: MIT
License-File: LICENSE.md
Classifier: Development Status :: 4 - Beta
Classifier: Intended Audience :: Developers
Classifier: Topic :: Multimedia :: Video
Classifier: Programming Language :: Python :: 3
Classifier: Programming Language :: Python :: 3.9
Classifier: Programming Language :: Python :: 3.10
Classifier: Programming Language :: Python :: 3.11
Classifier: Programming Language :: Python :: 3.12
Classifier: Programming Language :: Python :: 3.13
Classifier: Programming Language :: Python :: 3.14
Requires-Dist: numpy
Requires-Dist: pandas
Requires-Dist: plotille
Requires-Dist: tqdm
Requires-Python: >=3.9
Project-URL: Homepage, https://github.com/slhck/ffmpeg-bitrate-stats
Project-URL: Repository, https://github.com/slhck/ffmpeg-bitrate-stats
